{
    "progress_ms": 18372, 
    "timestamp": 1634544436794, 
    "repeat_state": "off", 
    "currently_playing_type": "track", 
    "shuffle_state": false, 
    "item": {
        "album": {
            "album_type": "single", 
            "name": "AV\u012aCI (01)", 
            "external_urls": {
                "spotify": "https://open.spotify.com/album/1m3mf7xkXIwssVriaaTjOS"
            }, 
            "release_date": "2017-08-10", 
            "uri": "spotify:album:1m3mf7xkXIwssVriaaTjOS", 
            "total_tracks": 6, 
                "href": "https://api.spotify.com/v1/albums/1m3mf7xkXIwssVriaaTjOS", 
                "artists": [{
                    "name": "Avicii", 
                    "external_urls": {
                        "spotify": "https://open.spotify.com/artist/1vCWHaC5f2uS3yhpwWbIA6"
                    }, 
                    "uri": "spotify:artist:1vCWHaC5f2uS3yhpwWbIA6", 
                    "href": "https://api.spotify.com/v1/artists/1vCWHaC5f2uS3yhpwWbIA6", 
                    "type": "artist", 
                    "id": "1vCWHaC5f2uS3yhpwWbIA6"
                }], 
                "images": [{
                    "url": "https://i.scdn.co/image/ab67616d0000b273a26cc58b4d64c2ece3376389", 
                    "width": 640, 
                    "height": 640
                    }, {
                    "url": "https://i.scdn.co/image/ab67616d00001e02a26cc58b4d64c2ece3376389", 
                    "width": 300, 
                    "height": 300
                    }, {
                    "url": "https://i.scdn.co/image/ab67616d00004851a26cc58b4d64c2ece3376389", 
                    "width": 64, 
                    "height": 64
                    }], 
                    "type": "album", 
                    "id": "1m3mf7xkXIwssVriaaTjOS", 
                    "available_markets": ["AD", "AE", "AG", "AL", "AM", "AO", "AR", "AT", "AU", "AZ", "BA", "BB", "BD", "BE", "BF", "BG", "BH", "BI", "BJ", "BN", "BO", "BR", "BS", "BT", "BW", "BY", "BZ", "CA", "CH", "CI", "CL", "CM", "CO", "CR", "CV", "CW", "CY", "CZ", "DE", "DJ", "DK", "DM", "DO", "DZ", "EC", "EE", "EG", "ES", "FI", "FJ", "FM", "FR", "GA", "GB", "GD", "GE", "GH", "GM", "GN", "GQ", "GR", "GT", "GW", "GY", "HK", "HN", "HR", "HT", "HU", "ID", "IE", "IL", "IN", "IS", "IT", "JM", "JO", "JP", "KE", "KG", "KH", "KI", "KM", "KN", "KR", "KW", "KZ", "LA", "LB", "LC", "LI", "LK", "LR", "LS", "LT", "LU", "LV", "MA", "MC", "MD", "ME", "MG", "MH", "MK", "ML", "MN", "MO", "MR", "MT", "MU", "MV", "MW", "MX", "MY", "MZ", "NA", "NE", "NG", "NI", "NL", "NO", "NP", "NR", "NZ", "OM", "PA", "PE", "PG", "PH", "PK", "PL", "PS", "PT", "PW", "PY", "QA", "RO", "RS", "RU", "RW", "SA", "SB", "SC", "SE", "SG", "SI", "SK", "SL", "SM", "SN", "SR", "ST", "SV", "SZ", "TD", "TG", "TH", "TL", "TN", "TO", "TR", "TT", "TV", "TW", "TZ", "UA", "UG", "US", "UY", "UZ", "VC", "VN", "VU", "WS", "XK", "ZA", "ZM", "ZW"], 
                    "release_date_precision": "day"
                    }, 
        "is_local": false, 
        "name": "What Would I Change It To (feat. Aluna)", 
        "uri": "spotify:track:1vkXc8Tz3dZGNZoU2WF3la", 
        "external_urls": {
            "spotify": "https://open.spotify.com/track/1vkXc8Tz3dZGNZoU2WF3la"
        }, 
        "popularity": 55, 
        "explicit": false, 
        "preview_url": "https://p.scdn.co/mp3-preview/4bb92c69a62f00c629f99867077fbc9d75b309dd?cid=3be5443f43b14ef587f68864ed10b641", 
        "track_number": 5, 
        "disc_number": 1, 
        "href": "https://api.spotify.com/v1/tracks/1vkXc8Tz3dZGNZoU2WF3la", 
        "artists": [{
            "name": "Avicii", 
            "external_urls": {
                "spotify": "https://open.spotify.com/artist/1vCWHaC5f2uS3yhpwWbIA6"
            }, 
            "uri": "spotify:artist:1vCWHaC5f2uS3yhpwWbIA6", 
            "href": "https://api.spotify.com/v1/artists/1vCWHaC5f2uS3yhpwWbIA6", 
            "type": "artist", "id": "1vCWHaC5f2uS3yhpwWbIA6"
        }, 
        {
            "name": "Aluna", 
            "external_urls": {
                "spotify": "https://open.spotify.com/artist/5ITI6SEoUZMIXXkzCfr4oE"
                }, 
            "uri": "spotify:artist:5ITI6SEoUZMIXXkzCfr4oE", 
            "href": "https://api.spotify.com/v1/artists/5ITI6SEoUZMIXXkzCfr4oE", 
            "type": "artist", 
            "id": "5ITI6SEoUZMIXXkzCfr4oE"
        }], 
        "duration_ms": 185454, 
        "external_ids": {"isrc": "SE5R71700105"}, 
        "type": "track", 
        "id": "1vkXc8Tz3dZGNZoU2WF3la", 
        "available_markets": ["AD", "AE", "AG", "AL", "AM", "AO", "AR", "AT", "AU", "AZ", "BA", "BB", "BD", "BE", "BF", "BG", "BH", "BI", "BJ", "BN", "BO", "BR", "BS", "BT", "BW", "BY", "BZ", "CA", "CH", "CI", "CL", "CM", "CO", "CR", "CV", "CW", "CY", "CZ", "DE", "DJ", "DK", "DM", "DO", "DZ", "EC", "EE", "EG", "ES", "FI", "FJ", "FM", "FR", "GA", "GB", "GD", "GE", "GH", "GM", "GN", "GQ", "GR", "GT", "GW", "GY", "HK", "HN", "HR", "HT", "HU", "ID", "IE", "IL", "IN", "IS", "IT", "JM", "JO", "JP", "KE", "KG", "KH", "KI", "KM", "KN", "KR", "KW", "KZ", "LA", "LB", "LC", "LI", "LK", "LR", "LS", "LT", "LU", "LV", "MA", "MC", "MD", "ME", "MG", "MH", "MK", "ML", "MN", "MO", "MR", "MT", "MU", "MV", "MW", "MX", "MY", "MZ", "NA", "NE", "NG", "NI", "NL", "NO", "NP", "NR", "NZ", "OM", "PA", "PE", "PG", "PH", "PK", "PL", "PS", "PT", "PW", "PY", "QA", "RO", "RS", "RU", "RW", "SA", "SB", "SC", "SE", "SG", "SI", "SK", "SL", "SM", "SN", "SR", "ST", "SV", "SZ", "TD", "TG", "TH", "TL", "TN", "TO", "TR", "TT", "TV", "TW", "TZ", "UA", "UG", "US", "UY", "UZ", "VC", "VN", "VU", "WS", "XK", "ZA", "ZM", "ZW"]}, 
    "actions": {"disallows": {"resuming": true}}, 
    "context": {"href": "https://api.spotify.com/v1/playlists/5NWZcukpNgj2NNv4eY9foR", "type": "playlist", "uri": "spotify:playlist:5NWZcukpNgj2NNv4eY9foR", "external_urls": {"spotify": "https://open.spotify.com/playlist/5NWZcukpNgj2NNv4eY9foR"}}, 
    "device": {"name": "JAVI-PC", "volume_percent": 99, "is_private_session": false, "is_active": true, "is_restricted": false, "type": "Computer", "id": "ab7546d01729b5ff3ffca5b82e2b8f01508472fd"}, 
    "is_playing": true}